{
  "db_name": "PostgreSQL",
  "query": "SELECT name, player_id FROM player WHERE player_id = ANY($1::integer[])",
  "describe": {
    "columns": [
      {
        "ordinal": 0,
        "name": "name",
        "type_info": "Text"
      },
      {
        "ordinal": 1,
        "name": "player_id",
        "type_info": "Int4"
      }
    ],
    "parameters": {
      "Left": [
        "Int4Array"
      ]
    },
    "nullable": [
      false,
      false
    ]
  },
  "hash": "9232699b3fcd101186b6e0d301637aa99b99348dde199611ea35296e4c493577"
}
